insta_science/__init__.py
insta_science/__main__.py
insta_science/shim.py
insta_science/util.py
insta_science/_internal/__init__.py
insta_science/_internal/a_scie.py
insta_science/_internal/bytes.py
insta_science/_internal/cache.py
insta_science/_internal/colors.py
insta_science/_internal/du.py
insta_science/_internal/errors.py
insta_science/_internal/fetcher.py
insta_science/_internal/hashing.py
insta_science/_internal/model.py
insta_science/_internal/parser.py
insta_science/_internal/platform.py
insta_science/_internal/project.py
insta_science/_internal/science.py
insta_science/_internal/version.py
insta_science-0.8.0.dist-info/METADATA
insta_science-0.8.0.dist-info/WHEEL
insta_science-0.8.0.dist-info/entry_points.txt
insta_science-0.8.0.dist-info/top_level.txt
insta_science-0.8.0.dist-info/pylock/pylock.toml
insta_science-0.8.0.dist-info/RECORD
