Metadata-Version: 2.4
Name: insta-science
Version: 0.8.0
Summary: A tool to help with installing and using `science` in Python projects.
Author-email: John Sirois <john.sirois@gmail.com>
Project-URL: Repository, https://github.com/a-scie/science-installers/tree/main/python
Project-URL: Bug Tracker, https://github.com/a-scie/science-installers/issues
Project-URL: Changelog, https://github.com/a-scie/science-installers/blob/main/python/CHANGES.md
Keywords: automation,command,runner,testing
Classifier: Development Status :: 3 - Alpha
Classifier: Intended Audience :: Developers
Classifier: License :: OSI Approved :: Apache Software License
Classifier: Operating System :: MacOS :: MacOS X
Classifier: Operating System :: Microsoft :: Windows
Classifier: Operating System :: POSIX :: Linux
Classifier: Operating System :: Unix
Classifier: Programming Language :: Python
Classifier: Programming Language :: Python :: 3 :: Only
Classifier: Programming Language :: Python :: 3.8
Classifier: Programming Language :: Python :: 3.9
Classifier: Programming Language :: Python :: 3.10
Classifier: Programming Language :: Python :: 3.11
Classifier: Programming Language :: Python :: 3.12
Classifier: Programming Language :: Python :: 3.13
Classifier: Topic :: Software Development :: Build Tools
Classifier: Topic :: Utilities
Requires-Python: >=3.8
Requires-Dist: ansicolors
Requires-Dist: appdirs
Requires-Dist: colorama; sys_platform == "win32"
Requires-Dist: filelock
Requires-Dist: httpx
Requires-Dist: packaging
Requires-Dist: tenacity
Requires-Dist: tomli; python_version < "3.11"
Requires-Dist: tqdm
Requires-Dist: typing-extensions
